
{
    "left":[
        {
            "icon" : "0px -22px",
            "txt" : "收藏鲜花礼品网(hua.com)"
        },
        {
            "icon" : "-24px -22px",
            "txt" : "关注微信",
            "img" : "ia_200000135.png",
            "info":"扫描关注"
        },
        {
            "icon" : "-48px -22px",
            "txt" : "花礼网app",
            "img" : "ia_200000134.png",
            "info" : "新人享100元App红包"
        }
    ],
    "right":[
        {
        
            "txt" : "你好，请登录"
        },
        {
         
            "txt" : "注册"
        },
        {
    
            "txt" : "订单查询"
        },
        {
         
            "txt" : "客户服务",
            "sel" : [
                "在线付款",
                "帮助中心",
                "售后服务",
                "配送范围",
                "留言反馈"
            ]
        },
        {
    
            "txt" : "购物车(0)"
        },
        {
         
            "txt" : "鲜花礼品网:国内领先鲜花网品牌"
        }
    ]
}